Metadata-Version: 1.1
Name: django-social-login
Version: 0.2.0
Summary: A Django APP for Social account login via OAuth2 Service
Home-page: https://github.com/yueyoum/django-social-login
Author: Wang Chao
Author-email: yueyoum@gmail.com
License: BSD
Keywords: social,oauth,oauth2,django,login
Platform: UNKNOWN
Classifier: Development Status :: 4 - Beta
Classifier: Topic :: Internet
Classifier: License :: OSI Approved :: BSD License
Classifier: Operating System :: OS Independent
Classifier: Programming Language :: Python
